aws_lambda_python_packager/__init__.py
aws_lambda_python_packager/__main__.py
aws_lambda_python_packager/arrow_fetcher.py
aws_lambda_python_packager/cli/__init__.py
aws_lambda_python_packager/cli/build.py
aws_lambda_python_packager/cli/unify.py
aws_lambda_python_packager/dep_analyzer.py
aws_lambda_python_packager/lambda_packager.py
aws_lambda_python_packager/pip_analyzer.py
aws_lambda_python_packager/poetry_analyzer.py
aws_lambda_python_packager/py.typed
aws_lambda_python_packager/util.py
aws_lambda_python_packager-1.4.4.dist-info/LICENSE
aws_lambda_python_packager-1.4.4.dist-info/METADATA
aws_lambda_python_packager-1.4.4.dist-info/WHEEL
aws_lambda_python_packager-1.4.4.dist-info/entry_points.txt
aws_lambda_python_packager-1.4.4.dist-info/RECORD
