Metadata-Version: 2.1
Name: aws-lambda-python-packager
Version: 1.4.4
Summary: Description
Home-page: https://github.com/mumblepins/aws-lambda-python-packager/
License: LGPL-3.0-or-later
Author: Daniel Sullivan
Author-email: mumblepins@users.noreply.github.com
Requires-Python: >=3.8,<4.0
Classifier: License :: OSI Approved :: GNU Lesser General Public License v3 or later (LGPLv3+)
Classifier: Programming Language :: Python :: 3
Classifier: Programming Language :: Python :: 3.8
Classifier: Programming Language :: Python :: 3.9
Classifier: Programming Language :: Python :: 3.10
Classifier: Programming Language :: Python :: 3.11
Requires-Dist: aiohttp
Requires-Dist: appdirs
Requires-Dist: click (>=7)
Requires-Dist: click-log
Requires-Dist: click-option-group
Requires-Dist: fsspec (>=2020.0,!=2022.10.0)
Requires-Dist: python-certifi-win32 ; platform_system == "Windows"
Requires-Dist: requests
Requires-Dist: toml (>=0.10)
Requires-Dist: wheel
Project-URL: Documentation, https://mumblepins.github.io/aws-lambda-python-packager/
Project-URL: Repository, https://github.com/mumblepins/aws-lambda-python-packager/
